graphene_resolver/__init__.py
graphene_resolver/connection.py
graphene_resolver/processor.py
graphene_resolver/resolver.py
graphene_resolver/schema.py
graphene_resolver/typedef.py
graphene_resolver/types/__init__.py
graphene_resolver/types/duration.py
graphene_resolver-0.1.10.dist-info/LICENSE
graphene_resolver-0.1.10.dist-info/WHEEL
graphene_resolver-0.1.10.dist-info/METADATA
graphene_resolver-0.1.10.dist-info/RECORD
