Metadata-Version: 2.1
Name: graphene-resolver
Version: 0.1.10
Summary: Using mongoose-like schema to write apollo-like resolver for graphene.
Home-page: https://github.com/NateScarlet/graphene-resolver
Author: NateScarlet
Author-email: NateScarlet@Gmail.com
Requires-Python: >=3.6,<4.0
Classifier: Intended Audience :: Developers
Classifier: Programming Language :: Python :: 3
Classifier: Programming Language :: Python :: 3.6
Classifier: Programming Language :: Python :: 3.7
Classifier: Programming Language :: Python :: 3.8
Classifier: Topic :: Software Development :: Libraries :: Python Modules
Requires-Dist: dataclasses (>=0.7,<0.8); python_version >= "3.6" and python_version < "3.7"
Requires-Dist: graphene (>=2.1,<3.0)
Requires-Dist: isodate (>=0.6,<0.7)
Requires-Dist: lazy-object-proxy (>=1.4,<2.0)
Requires-Dist: phrases-case (>=0.1.1,<0.2.0)
Project-URL: Documentation, https://natescarlet.github.io/graphene-resolver/
Project-URL: Repository, https://github.com/NateScarlet/graphene-resolver
